MANIFEST.in
setup.cfg
setup.py
infi.pyvisdk.egg-info/PKG-INFO
infi.pyvisdk.egg-info/SOURCES.txt
infi.pyvisdk.egg-info/dependency_links.txt
infi.pyvisdk.egg-info/requires.txt
infi.pyvisdk.egg-info/top_level.txt
pyvisdk/__init__.py
pyvisdk/app.py
pyvisdk/client.py
pyvisdk/core.py
pyvisdk/exceptions.py
pyvisdk/options.py
pyvisdk/transport.py
pyvisdk/utils.py
pyvisdk/vim.py
pyvisdk/base/__init__.py
pyvisdk/base/base_entity.py
pyvisdk/base/data_object_types.py
pyvisdk/base/managed_object_types.py
pyvisdk/do/__init__.py
pyvisdk/do/about_info.py
pyvisdk/do/account_created_event.py
pyvisdk/do/account_removed_event.py
pyvisdk/do/account_updated_event.py
pyvisdk/do/action.py
pyvisdk/do/active_directory_fault.py
pyvisdk/do/active_directory_profile.py
pyvisdk/do/admin_disabled.py
pyvisdk/do/admin_not_disabled.py
pyvisdk/do/admin_password_not_changed_event.py
pyvisdk/do/affinity_configured.py
pyvisdk/do/after_startup_task_scheduler.py
pyvisdk/do/agent_install_failed.py
pyvisdk/do/alarm_acknowledged_event.py
pyvisdk/do/alarm_action.py
pyvisdk/do/alarm_action_triggered_event.py
pyvisdk/do/alarm_cleared_event.py
pyvisdk/do/alarm_created_event.py
pyvisdk/do/alarm_description.py
pyvisdk/do/alarm_email_completed_event.py
pyvisdk/do/alarm_email_failed_event.py
pyvisdk/do/alarm_event.py
pyvisdk/do/alarm_event_argument.py
pyvisdk/do/alarm_expression.py
pyvisdk/do/alarm_info.py
pyvisdk/do/alarm_reconfigured_event.py
pyvisdk/do/alarm_removed_event.py
pyvisdk/do/alarm_script_complete_event.py
pyvisdk/do/alarm_script_failed_event.py
pyvisdk/do/alarm_setting.py
pyvisdk/do/alarm_snmp_completed_event.py
pyvisdk/do/alarm_snmp_failed_event.py
pyvisdk/do/alarm_spec.py
pyvisdk/do/alarm_state.py
pyvisdk/do/alarm_status_changed_event.py
pyvisdk/do/alarm_triggering_action.py
pyvisdk/do/alarm_triggering_action_transition_spec.py
pyvisdk/do/all_virtual_machines_licensed_event.py
pyvisdk/do/already_authenticated_session_event.py
pyvisdk/do/already_being_managed.py
pyvisdk/do/already_connected.py
pyvisdk/do/already_exists.py
pyvisdk/do/already_upgraded.py
pyvisdk/do/and_alarm_expression.py
pyvisdk/do/answer_file.py
pyvisdk/do/answer_file_create_spec.py
